odoo8_addon_event_product-8.0.1.0.0.99.dev15-py2.7-nspkg.pth
odoo_addons/event_product/__openerp__.py
odoo_addons/event_product/__init__.py
odoo_addons/event_product/exceptions.py
odoo_addons/event_product/README.rst
odoo_addons/event_product/models/product.py
odoo_addons/event_product/models/__init__.py
odoo_addons/event_product/models/event.py
odoo_addons/event_product/i18n/es.po
odoo_addons/event_product/views/product.xml
odoo_addons/event_product/views/event.xml
odoo_addons/event_product/tests/test_product.py
odoo_addons/event_product/tests/test_event.py
odoo_addons/event_product/tests/__init__.py
odoo_addons/event_product/tests/base.py
odoo_addons/event_product/static/description/icon.png
odoo8_addon_event_product-8.0.1.0.0.99.dev15.dist-info/top_level.txt
odoo8_addon_event_product-8.0.1.0.0.99.dev15.dist-info/WHEEL
odoo8_addon_event_product-8.0.1.0.0.99.dev15.dist-info/RECORD
odoo8_addon_event_product-8.0.1.0.0.99.dev15.dist-info/metadata.json
odoo8_addon_event_product-8.0.1.0.0.99.dev15.dist-info/DESCRIPTION.rst
odoo8_addon_event_product-8.0.1.0.0.99.dev15.dist-info/METADATA
odoo8_addon_event_product-8.0.1.0.0.99.dev15.dist-info/namespace_packages.txt
